{"_type":"export","__export_format":4,"__export_date":"2024-07-28T21:27:28.935Z","__export_source":"insomnia.desktop.app:v9.3.2","resources":[{"_id":"req_4b6bfb2817e344ab82626c482ddc0d38","parentId":"fld_3b59358ddccd4cc68faeb7c026c5e349","modified":1722201726116,"created":1722189877262,"url":"{{ _.protocol }}://{{ _.host }}/api/public/galaxies/{{ _.active_galaxy }}","name":"Get Galaxy by ID","description":"","method":"GET","body":{},"parameters":[],"headers":[{"name":"User-Agent","value":"insomnia/9.3.2"}],"authentication":{},"metaSortKey":-1722201536376,"isPrivate":false,"pathParameters":[],"settingStoreCookies":true,"settingSendCookies":true,"settingDisableRenderRequestBody":false,"settingEncodeUrl":true,"settingRebuildPath":true,"settingFollowRedirects":"global","_type":"request"},{"_id":"fld_3b59358ddccd4cc68faeb7c026c5e349","parentId":"wrk_2e1ea73797b84fa5a4523c1dd47e5690","modified":1722201531127,"created":1722201531127,"name":"Galaxies","description":"","environment":{},"environmentPropertyOrder":null,"metaSortKey":-1722201531127,"_type":"request_group"},{"_id":"wrk_2e1ea73797b84fa5a4523c1dd47e5690","parentId":null,"modified":1722187005023,"created":1722187005023,"name":"TheUniverseVault","description":"","scope":"collection","_type":"workspace"},{"_id":"req_9e438970511a4a4ea78143e95568a9d6","parentId":"fld_3b59358ddccd4cc68faeb7c026c5e349","modified":1722201741056,"created":1722187010221,"url":"{{ _.protocol }}://{{ _.host }}/api/public/galaxies/","name":"New Galaxy","description":"","method":"POST","body":{"mimeType":"application/json","text":"{\n  \"name\": \"Milky Way\",\n  \"description\": \"The galaxy that contains our Solar System.\",\n  \"type\": \"Barred Spiral\",\n  \"mass\": 1.5e42,\n  \"diameter\": 105700,\n  \"number_of_stars\": 100000000000,\n  \"distance_from_earth\": 0,\n  \"has_supermassive_black_hole\": true,\n  \"metallicity\": 0.02,\n  \"velocity\": 552,\n  \"discovery_date\": \"1920-01-01T00:00:00\",\n  \"discovery_method\": \"Ancient Observation\",\n  \"discovery_status\": \"Confirmed\",\n  \"discovered_by\": \"Various Ancient Astronomers\"\n}\n"},"parameters":[],"headers":[{"name":"Content-Type","value":"application/json"},{"name":"User-Agent","value":"insomnia/9.3.2"}],"authentication":{},"metaSortKey":-1722201536326,"isPrivate":false,"pathParameters":[],"settingStoreCookies":true,"settingSendCookies":true,"settingDisableRenderRequestBody":false,"settingEncodeUrl":true,"settingRebuildPath":true,"settingFollowRedirects":"global","_type":"request"},{"_id":"req_f02f090c17824f5784af2c7aded47df5","parentId":"fld_3b59358ddccd4cc68faeb7c026c5e349","modified":1722201744999,"created":1722189669384,"url":"{{ _.protocol }}://{{ _.host }}/api/public/galaxies/{{ _.active_galaxy }}","name":"Get all Galaxies","description":"","method":"GET","body":{},"parameters":[],"headers":[{"name":"User-Agent","value":"insomnia/9.3.2"}],"authentication":{},"metaSortKey":-1722201536276,"isPrivate":false,"pathParameters":[],"settingStoreCookies":true,"settingSendCookies":true,"settingDisableRenderRequestBody":false,"settingEncodeUrl":true,"settingRebuildPath":true,"settingFollowRedirects":"global","_type":"request"},{"_id":"req_1701c654757a4946a741b43fb2edd556","parentId":"fld_91919c8631fb4844b0bca24ebd008448","modified":1722201751378,"created":1722190799968,"url":"{{ _.protocol }}://{{ _.host }}/api/public/galaxies/{{ _.active_galaxy }}/solar-systems/","name":"New Solar System","description":"","method":"POST","body":{"mimeType":"application/json","text":"{\n  \"name\": \"Solar System\",\n  \"description\": \"The planetary system that includes the Earth and the Sun.\",\n  \"age\": 4.6e9,\n  \"distance_from_earth\": 0,\n  \"has_life\": true,\n  \"habitable_zones\": 1,\n  \"discovery_date\": \"1543-01-01T00:00:00\",\n  \"discovery_method\": \"Heliocentric Model\",\n  \"discovery_status\": \"Confirmed\",\n  \"discovered_by\": \"Nicolaus Copernicus\"\n}\n"},"parameters":[],"headers":[{"name":"Content-Type","value":"application/json"},{"name":"User-Agent","value":"insomnia/9.3.2"}],"authentication":{},"metaSortKey":-1722201539859,"isPrivate":false,"pathParameters":[],"settingStoreCookies":true,"settingSendCookies":true,"settingDisableRenderRequestBody":false,"settingEncodeUrl":true,"settingRebuildPath":true,"settingFollowRedirects":"global","_type":"request"},{"_id":"fld_91919c8631fb4844b0bca24ebd008448","parentId":"wrk_2e1ea73797b84fa5a4523c1dd47e5690","modified":1722201522645,"created":1722201522645,"name":"Solar Systems","description":"","environment":{},"environmentPropertyOrder":null,"metaSortKey":-1722201522645,"_type":"request_group"},{"_id":"req_7b8a23bc448e4abb84749b6751dfe2ce","parentId":"fld_91919c8631fb4844b0bca24ebd008448","modified":1722201992451,"created":1722198255694,"url":"{{ _.protocol }}://{{ _.host }}/api/public/galaxies/{{ _.active_galaxy }}/solar-systems/{{ _.active_solar_system }}","name":"Get Solar System by ID","description":"","method":"GET","body":{},"parameters":[],"headers":[{"name":"User-Agent","value":"insomnia/9.3.2"}],"authentication":{},"metaSortKey":-1722201539759,"isPrivate":false,"pathParameters":[],"settingStoreCookies":true,"settingSendCookies":true,"settingDisableRenderRequestBody":false,"settingEncodeUrl":true,"settingRebuildPath":true,"settingFollowRedirects":"global","_type":"request"},{"_id":"req_c73eda481a254d1a9de1d2d3a423b0c8","parentId":"fld_91919c8631fb4844b0bca24ebd008448","modified":1722201772594,"created":1722198084175,"url":"{{ _.protocol }}://{{ _.host }}/api/public/galaxies/{{ _.active_galaxy }}/solar-systems/","name":"Get all Solar Systems","description":"","method":"GET","body":{},"parameters":[],"headers":[{"name":"User-Agent","value":"insomnia/9.3.2"}],"authentication":{},"metaSortKey":-1722201539659,"isPrivate":false,"pathParameters":[],"settingStoreCookies":true,"settingSendCookies":true,"settingDisableRenderRequestBody":false,"settingEncodeUrl":true,"settingRebuildPath":true,"settingFollowRedirects":"global","_type":"request"},{"_id":"req_444eda4371274274aa48285feb63ce6e","parentId":"fld_3d8e118ca86946ccb48e1f4c6cf7a438","modified":1722201981288,"created":1722199044668,"url":"{{ _.protocol }}://{{ _.host }}/api/public/galaxies/{{ _.active_galaxy }}solar-systems/{{ _.active_solar_system }}/stars/66a6a4ec54fe0884cbb55142","name":"Star by ID","description":"","method":"GET","body":{},"parameters":[],"headers":[{"name":"User-Agent","value":"insomnia/9.3.2"}],"authentication":{},"metaSortKey":-1722201576403,"isPrivate":false,"pathParameters":[],"settingStoreCookies":true,"settingSendCookies":true,"settingDisableRenderRequestBody":false,"settingEncodeUrl":true,"settingRebuildPath":true,"settingFollowRedirects":"global","_type":"request"},{"_id":"fld_3d8e118ca86946ccb48e1f4c6cf7a438","parentId":"wrk_2e1ea73797b84fa5a4523c1dd47e5690","modified":1722201517248,"created":1722201517248,"name":"Stars","description":"","environment":{},"environmentPropertyOrder":null,"metaSortKey":-1722201517248,"_type":"request_group"},{"_id":"req_cc2f63b8ed8844fa813fb01fbf29db02","parentId":"fld_3d8e118ca86946ccb48e1f4c6cf7a438","modified":1722201971748,"created":1722198486613,"url":"{{ _.protocol }}://{{ _.host }}/api/public/galaxies/{{ _.active_galaxy }}/solar-systems/{{ _.active_solar_system }}/stars/","name":"Get all Stars","description":"","method":"GET","body":{},"parameters":[],"headers":[{"name":"User-Agent","value":"insomnia/9.3.2"}],"authentication":{},"metaSortKey":-1722201576353,"isPrivate":false,"pathParameters":[],"settingStoreCookies":true,"settingSendCookies":true,"settingDisableRenderRequestBody":false,"settingEncodeUrl":true,"settingRebuildPath":true,"settingFollowRedirects":"global","_type":"request"},{"_id":"req_96d9660950ee4c4492746c9b34a2f768","parentId":"fld_3d8e118ca86946ccb48e1f4c6cf7a438","modified":1722201955639,"created":1722193261761,"url":"{{ _.protocol }}://{{ _.host }}/api/public/galaxies/{{ _.active_galaxy }}/solar-systems/{{ _.active_solar_system }}/stars/","name":"New Star","description":"","method":"POST","body":{"mimeType":"application/json","text":"{\n  \"name\": \"Sun\",\n  \"description\": \"The star at the center of our Solar System.\",\n  \"type\": \"G-type main-sequence star (G2V)\",\n  \"mass\": 1.989e30,\n  \"radius\": 696340,\n  \"luminosity\": 3.828e26,\n  \"temperature\": 5778,\n  \"age\": 4.6e9,\n  \"has_planetary_system\": true,\n  \"metallicity\": 0.0122,\n  \"rotation_velocity\": 1.997,\n  \"discovery_date\": \"1543-01-01T00:00:00\",\n  \"discovery_method\": \"Ancient Observation\",\n  \"discovery_status\": \"Confirmed\",\n  \"discovered_by\": \"Various Ancient Astronomers\"\n}\n"},"parameters":[],"headers":[{"name":"Content-Type","value":"application/json"},{"name":"User-Agent","value":"insomnia/9.3.2"}],"authentication":{},"metaSortKey":-1722201576303,"isPrivate":false,"pathParameters":[],"settingStoreCookies":true,"settingSendCookies":true,"settingDisableRenderRequestBody":false,"settingEncodeUrl":true,"settingRebuildPath":true,"settingFollowRedirects":"global","_type":"request"},{"_id":"req_59fdb929c7df41a9aa72d2d717dfc902","parentId":"fld_373f7f42f64f4b3abebcd8884c964e0e","modified":1722201940313,"created":1722199567458,"url":"{{ _.protocol }}://{{ _.host }}/api/public/galaxies/{{ _.active_galaxy }}/solar-systems/{{ _.active_solar_system }}/planets/{{ _.active_planet }}","name":"Get Planet by ID","description":"","method":"GET","body":{},"parameters":[],"headers":[{"name":"User-Agent","value":"insomnia/9.3.2"}],"authentication":{},"metaSortKey":-1722201597674,"isPrivate":false,"pathParameters":[],"settingStoreCookies":true,"settingSendCookies":true,"settingDisableRenderRequestBody":false,"settingEncodeUrl":true,"settingRebuildPath":true,"settingFollowRedirects":"global","_type":"request"},{"_id":"fld_373f7f42f64f4b3abebcd8884c964e0e","parentId":"wrk_2e1ea73797b84fa5a4523c1dd47e5690","modified":1722201509312,"created":1722201509312,"name":"Planets","description":"","environment":{},"environmentPropertyOrder":null,"metaSortKey":-1722201509312,"_type":"request_group"},{"_id":"req_873af964544c41c397898f7f85189abd","parentId":"fld_373f7f42f64f4b3abebcd8884c964e0e","modified":1722201918877,"created":1722199524843,"url":"{{ _.protocol }}://{{ _.host }}/api/public/galaxies/{{ _.active_galaxy }}/solar-systems/{{ _.active_solar_system }}/planets/","name":"Get all Planets","description":"","method":"GET","body":{},"parameters":[],"headers":[{"name":"User-Agent","value":"insomnia/9.3.2"}],"authentication":{},"metaSortKey":-1722201597624,"isPrivate":false,"pathParameters":[],"settingStoreCookies":true,"settingSendCookies":true,"settingDisableRenderRequestBody":false,"settingEncodeUrl":true,"settingRebuildPath":true,"settingFollowRedirects":"global","_type":"request"},{"_id":"req_c7a800ef4e0a4985a9f1082463bcc3e6","parentId":"fld_373f7f42f64f4b3abebcd8884c964e0e","modified":1722201911881,"created":1722195005660,"url":"{{ _.protocol }}://{{ _.host }}/api/public/galaxies/{{ _.active_galaxy }}/solar-systems/{{ _.active_solar_system }}/planets/","name":"New Planet","description":"","method":"POST","body":{"mimeType":"application/json","text":"{\n  \"name\": \"Earth\",\n  \"description\": \"The third planet from the Sun and the only known planet to support life.\",\n  \"gravity\": 9.81,\n  \"diameter\": 12742,\n  \"mass\": 5.972e24,\n  \"rotation_period\": 24,\n  \"orbital_period\": 365,\n  \"has_atmosphere\": true,\n  \"terrain\": \"Varied, including mountains, plains, and oceans\",\n  \"surface_water\": 71,\n  \"temperature_day\": 288,\n  \"temperature_night\": 255,\n  \"kernel\": \"Solid core with a liquid outer core\",\n  \"age\": 4.6e9,\n  \"materials\": [\"Silicate rocks\", \"Metals\", \"Water\"],\n  \"has_life\": true,\n  \"has_ring_system\": false,\n  \"discovery_date\": \"0001-01-01T00:00:00\",\n  \"discovery_method\": \"Ancient Observation\",\n  \"discovery_status\": \"Confirmed\",\n  \"discovered_by\": \"Various Ancient Civilizations\"\n}\n"},"parameters":[],"headers":[{"name":"Content-Type","value":"application/json"},{"name":"User-Agent","value":"insomnia/9.3.2"}],"authentication":{},"metaSortKey":-1722201597574,"isPrivate":false,"pathParameters":[],"settingStoreCookies":true,"settingSendCookies":true,"settingDisableRenderRequestBody":false,"settingEncodeUrl":true,"settingRebuildPath":true,"settingFollowRedirects":"global","_type":"request"},{"_id":"req_365ded5303fb43c083ed19ed8b0734b7","parentId":"fld_e97610519ddd48dbb59a37e3d455ac74","modified":1722201902541,"created":1722199862248,"url":"{{ _.protocol }}://{{ _.host }}/api/public/galaxies/{{ _.active_galaxy }}/solar-systems/{{ _.active_solar_system }}/planets/{{ _.active_planet }}/moons/66a6a4ec54fe0884cbb55146","name":"Get Moon by ID","description":"","method":"GET","body":{},"parameters":[],"headers":[{"name":"User-Agent","value":"insomnia/9.3.2"}],"authentication":{},"metaSortKey":-1722201545174,"isPrivate":false,"pathParameters":[],"settingStoreCookies":true,"settingSendCookies":true,"settingDisableRenderRequestBody":false,"settingEncodeUrl":true,"settingRebuildPath":true,"settingFollowRedirects":"global","_type":"request"},{"_id":"fld_e97610519ddd48dbb59a37e3d455ac74","parentId":"wrk_2e1ea73797b84fa5a4523c1dd47e5690","modified":1722201512958,"created":1722201503459,"name":"Moons","description":"","environment":{},"environmentPropertyOrder":null,"metaSortKey":-1722201503459,"_type":"request_group"},{"_id":"req_e481c28e0d9643ad94b411efd39fd65d","parentId":"fld_e97610519ddd48dbb59a37e3d455ac74","modified":1722201880578,"created":1722195394960,"url":"{{ _.protocol }}://{{ _.host }}/api/public/galaxies/{{ _.active_galaxy }}/solar-systems/{{ _.active_solar_system }}/planets/{{ _.active_planet }}/moons/","name":"New Moon","description":"","method":"POST","body":{"mimeType":"application/json","text":"{\n  \"name\": \"Moon\",\n  \"description\": \"Earth's only natural satellite, known for its phases and influence on tides.\",\n  \"gravity\": 1.625,\n  \"diameter\": 3474,\n  \"mass\": 7.342e22,\n  \"rotation_period\": 655.7,\n  \"orbital_period\": 27.32,\n  \"has_atmosphere\": false,\n  \"terrain\": \"Rocky with craters and plains\",\n  \"surface_water\": 0,\n  \"temperature_day\": 390,\n  \"temperature_night\": 260,\n  \"kernel\": \"Solid\",\n  \"age\": 4.5e9,\n  \"materials\": [\"Silicate rocks\", \"Metals\"],\n  \"has_life\": false,\n  \"discovery_date\": \"0001-01-01T00:00:00\",\n  \"discovery_method\": \"Ancient Observation\",\n  \"discovery_status\": \"Confirmed\",\n  \"discovered_by\": \"Various Ancient Civilizations\"\n}\n"},"parameters":[],"headers":[{"name":"Content-Type","value":"application/json"},{"name":"User-Agent","value":"insomnia/9.3.2"}],"authentication":{},"metaSortKey":-1722201545124,"isPrivate":false,"pathParameters":[],"settingStoreCookies":true,"settingSendCookies":true,"settingDisableRenderRequestBody":false,"settingEncodeUrl":true,"settingRebuildPath":true,"settingFollowRedirects":"global","_type":"request"},{"_id":"req_da95fa854a3f4670bef060d5801c10bf","parentId":"fld_e97610519ddd48dbb59a37e3d455ac74","modified":1722201851968,"created":1722199801625,"url":"{{ _.protocol }}://{{ _.host }}/api/public/galaxies/{{ _.active_galaxy }}solar-systems/{{ _.active_solar_system }}/planets/{{ _.active_planet }}/moons","name":"Get all Moons","description":"","method":"GET","body":{},"parameters":[],"headers":[{"name":"User-Agent","value":"insomnia/9.3.2"}],"authentication":{},"metaSortKey":-1722201545074,"isPrivate":false,"pathParameters":[],"settingStoreCookies":true,"settingSendCookies":true,"settingDisableRenderRequestBody":false,"settingEncodeUrl":true,"settingRebuildPath":true,"settingFollowRedirects":"global","_type":"request"},{"_id":"env_5895a54ace9e51e11025dac0f8d980087ab6cf02","parentId":"wrk_2e1ea73797b84fa5a4523c1dd47e5690","modified":1722201698128,"created":1722187005044,"name":"Base Environment","data":{"protocol":"http","host":"127.0.0.1:8000","active_galaxy":"","active_solar_system":"","active_planet":""},"dataPropertyOrder":{"&":["protocol","host","active_galaxy","active_solar_system","active_planet"]},"color":null,"isPrivate":false,"metaSortKey":1722187005045,"_type":"environment"},{"_id":"jar_5895a54ace9e51e11025dac0f8d980087ab6cf02","parentId":"wrk_2e1ea73797b84fa5a4523c1dd47e5690","modified":1722187005046,"created":1722187005046,"name":"Default Jar","cookies":[],"_type":"cookie_jar"}]}